script_client/__init__.py
script_client/const.py
script_client/deco.py
script_client/file_manage.py
script_client/jobs.py
script_client/run_script.py
script_client/web_server.py
script_client/common/__init__.py
script_client/common/common_method.py
script_client/common/my_requests.py
script_client/static/__init__.py
script_client/static/css/__init__.py
script_client/static/css/bootstrap.min.css
script_client/static/css/fileinput.min.css
script_client/static/js/__init__.py
script_client/static/js/bootstrap.min.js
script_client/static/js/fileinput.min.js
script_client/static/js/jquery-3.4.1.min.js
script_client/templates/__init__.py
script_client/templates/upload.html
script_client-1.2.4.data/data/script_client/static/css/bootstrap.min.css
script_client-1.2.4.data/data/script_client/static/css/fileinput.min.css
script_client-1.2.4.data/data/script_client/static/js/bootstrap.min.js
script_client-1.2.4.data/data/script_client/static/js/fileinput.min.js
script_client-1.2.4.data/data/script_client/static/js/jquery-3.4.1.min.js
script_client-1.2.4.data/data/script_client/templates/upload.html
script_client-1.2.4.dist-info/METADATA
script_client-1.2.4.dist-info/WHEEL
script_client-1.2.4.dist-info/top_level.txt
script_client-1.2.4.dist-info/RECORD
